ssb_libtest7/__init__.py
ssb_libtest7/__main__.py
ssb_libtest7/functions.py
ssb_libtest7/py.typed
ssb_libtest7-0.0.1.dist-info/LICENSE
ssb_libtest7-0.0.1.dist-info/METADATA
ssb_libtest7-0.0.1.dist-info/WHEEL
ssb_libtest7-0.0.1.dist-info/entry_points.txt
ssb_libtest7-0.0.1.dist-info/RECORD
