Metadata-Version: 2.3
Name: ssb-libtest7
Version: 0.0.1
Summary: SSB Libtest7
License: MIT
Author: Henrik Bråthen
Author-email: bhe@ssb.no
Maintainer: Statistics Norway, Energy, environmental and transport statistics Department (425)
Requires-Python: >=3.10,<4.0
Classifier: Development Status :: 4 - Beta
Classifier: License :: OSI Approved :: MIT License
Classifier: Programming Language :: Python :: 3
Classifier: Programming Language :: Python :: 3.10
Classifier: Programming Language :: Python :: 3.11
Classifier: Programming Language :: Python :: 3.12
Classifier: Programming Language :: Python :: 3.13
Requires-Dist: click (>=8.0.1)
Project-URL: Changelog, https://github.com/statisticsnorway/ssb-libtest7/releases
Project-URL: Documentation, https://statisticsnorway.github.io/ssb-libtest7
Project-URL: Homepage, https://github.com/statisticsnorway/ssb-libtest7
Project-URL: Repository, https://github.com/statisticsnorway/ssb-libtest7
